{"version": "1", "message": "ERROR: Hidden Testcases server unreachable.", "problem_id": "ads2_m7_a1_1", "user_id": "chinuteja", "score": {"sample": {"0": {"execution_time": 0.7649698257446289, "passed": true}, "1": {"execution_time": 0.26821327209472656, "passed": true}, "2": {"execution_time": 0.38608813285827637, "passed": true}, "3": {"execution_time": 0.23287224769592285, "passed": true}, "4": {"execution_time": 0.21913790702819824, "passed": true}, "5": {"execution_time": 0.20762109756469727, "passed": true}}}, "check_style_score": "0/1"}