{"version": "1", "message": "ERROR: Hidden Testcases server unreachable.", "problem_id": "ads2_m1_a1_1", "user_id": "chinuteja", "score": {"sample": {"0": {"execution_time": 0.21823573112487793, "passed": true}, "1": {"execution_time": 0.18723034858703613, "passed": true}, "2": {"execution_time": 0.23299884796142578, "passed": false}, "3": {"execution_time": 0.2461848258972168, "passed": true}, "4": {"execution_time": 0.21315288543701172, "passed": true}, "5": {"execution_time": 0.2267146110534668, "passed": true}, "6": {"execution_time": 0.21372103691101074, "passed": true}, "7": {"execution_time": 0.2132411003112793, "passed": true}}}, "check_style_score": "1/1"}