{"version": "1", "message": "ERROR: Hidden Testcases server unreachable.", "problem_id": "ads2_m1_a1_1", "user_id": "chinuteja", "score": {"sample": {"0": {"execution_time": 0.17828607559204102, "passed": true}, "1": {"execution_time": 0.19665813446044922, "passed": true}, "2": {"execution_time": 0.23237252235412598, "passed": false}, "3": {"execution_time": 0.2012014389038086, "passed": true}, "4": {"execution_time": 0.195648193359375, "passed": true}, "5": {"execution_time": 0.20551276206970215, "passed": true}, "6": {"execution_time": 0.20810580253601074, "passed": true}, "7": {"execution_time": 0.21591424942016602, "passed": true}}}, "check_style_score": "0/1"}